nexpose/__init__.py
nexpose/json_utils.py
nexpose/nexpose.py
nexpose/nexpose_asset.py
nexpose/nexpose_assetfilter.py
nexpose/nexpose_assetgroup.py
nexpose/nexpose_backup.py
nexpose/nexpose_credential.py
nexpose/nexpose_criteria.py
nexpose/nexpose_criteria_constants.py
nexpose/nexpose_criteria_fields.py
nexpose/nexpose_criteria_operators.py
nexpose/nexpose_discoveryconnection.py
nexpose/nexpose_engine.py
nexpose/nexpose_enginepool.py
nexpose/nexpose_node.py
nexpose/nexpose_privileges.py
nexpose/nexpose_report.py
nexpose/nexpose_role.py
nexpose/nexpose_scansummary.py
nexpose/nexpose_sharedcredential.py
nexpose/nexpose_site.py
nexpose/nexpose_status.py
nexpose/nexpose_tag.py
nexpose/nexpose_ticket.py
nexpose/nexpose_user.py
nexpose/nexpose_userauthenticator.py
nexpose/nexpose_vulnerability.py
nexpose/nexpose_vulnerabilityexception.py
nexpose/python_utils.py
nexpose/xml_utils.py
nexpose-0.1.7.dist-info/DESCRIPTION.rst
nexpose-0.1.7.dist-info/METADATA
nexpose-0.1.7.dist-info/RECORD
nexpose-0.1.7.dist-info/WHEEL
nexpose-0.1.7.dist-info/metadata.json
nexpose-0.1.7.dist-info/top_level.txt
