Metadata-Version: 2.0
Name: nexpose
Version: 0.1.7
Summary: The official Python Nexpose API client library
Home-page: https://github.com/rapid7/nexpose-client-python
Author: Davinsi Labs
Author-email: UNKNOWN
License: BSD
Download-URL: https://github.com/rapid7/nexpose-client-python/releases
Keywords: nexpose,insightvm,rapid7
Platform: UNKNOWN
Classifier: Development Status :: 3 - Alpha
Classifier: Intended Audience :: Developers
Classifier: Natural Language :: English
Classifier: Programming Language :: Python
Classifier: Programming Language :: Python :: 2.6
Classifier: Programming Language :: Python :: 2.7
Classifier: Programming Language :: Python :: 3
Classifier: Programming Language :: Python :: 3.4
Classifier: Programming Language :: Python :: 3.5
Classifier: Programming Language :: Python :: 3.6
Requires-Dist: lxml
Requires-Dist: future
